p_cast/__main__.py
p_cast/app.py
p_cast/cast.py
p_cast/config.py
p_cast/device.py
p_cast/exceptions.py
p_cast/ffmpeg.py
p_cast/pipewire.py
p_cast-1.1.0.dist-info/licenses/LICENSE
p_cast-1.1.0.dist-info/METADATA
p_cast-1.1.0.dist-info/WHEEL
p_cast-1.1.0.dist-info/entry_points.txt
p_cast-1.1.0.dist-info/top_level.txt
p_cast-1.1.0.dist-info/RECORD
