Metadata-Version: 2.4
Name: p-cast
Version: 1.1.0
Summary: Cast audio from pipewire to chromecast device.
Project-URL: Homepage, https://github.com/GenessyX/p-cast
Project-URL: Repository, https://github.com/GenessyX/p-cast
Project-URL: Issues, https://github.com/GenessyX/p-cast/issues
Classifier: Development Status :: 4 - Beta
Classifier: Intended Audience :: End Users/Desktop
Classifier: Topic :: Multimedia :: Sound/Audio :: Capture/Recording
Classifier: Topic :: Multimedia :: Sound/Audio :: Players
Classifier: Topic :: Utilities
Classifier: Environment :: Console
Classifier: Operating System :: POSIX :: Linux
Classifier: Programming Language :: Python :: 3
Classifier: Programming Language :: Python :: 3.13
Classifier: License :: OSI Approved :: GNU General Public License v3 (GPLv3)
Requires-Python: >=3.12
License-File: LICENSE
Requires-Dist: granian>=2.2.5
Requires-Dist: pulsectl-asyncio>=1.2.2
Requires-Dist: pychromecast>=14.0.7
Requires-Dist: socketify>=0.0.31
Requires-Dist: starlette>=0.46.2
Requires-Dist: typed-ffmpeg>=2.7.3
Requires-Dist: uvicorn>=0.34.2
Requires-Dist: uvloop>=0.21.0
Dynamic: license-file
